nf_batch_runner/__init__.py
nf_batch_runner/aws.py
nf_batch_runner/cli.py
nf_batch_runner/click_helpers.py
nf_batch_runner/environment.py
nf_batch_runner-0.1.13.dist-info/METADATA
nf_batch_runner-0.1.13.dist-info/WHEEL
nf_batch_runner-0.1.13.dist-info/entry_points.txt
nf_batch_runner-0.1.13.dist-info/top_level.txt
nf_batch_runner-0.1.13.dist-info/RECORD
