Metadata-Version: 2.1
Name: nf-batch-runner
Version: 0.1.13
Summary: Installs nf-batch-runner in your AWS account
Home-page: https://gitlab.com/cgps/nf-batch-runner
Author: Centre for Genomic Pathogen Surveillance
Author-email: cgps@sanger.ac.uk
License: UNKNOWN
Project-URL: Source, https://gitlab.com/cgps/nf-batch-runner/
Keywords: aws batch nextflow bioinformatics pipeline
Platform: UNKNOWN
Classifier: Development Status :: 4 - Beta
Classifier: Programming Language :: Python :: 3
Classifier: Operating System :: OS Independent
Requires-Python: >=3
Requires-Dist: boto3 (>=1.9.227)
Requires-Dist: bcrypt (>=3.1.7)
Requires-Dist: Click (>=7.0)
Requires-Dist: PyYAML (>=5.1.2)
